{
    "tenantId": "mn.yairipok",
    "moduleName": "egov-location",
    "TenantBoundary": [
        {
            "hierarchyType": {
                "code": "REVENUE",
                "name": "REVENUE"
            },
            "boundary": {
                "id": 1,
                "boundaryNum": 1,
                "name": "Yairipok",
                "localname": "Yairipok",
                "longitude": null,
                "latitude": null,
                "label": "City",
                "code": "YAIRIPOK - 27",
                "children": [
                    {
                        "id": "1c5dbabd-e04a-44e1-ac27-1fea19fac28f",
                        "boundaryNum": 1,
                        "name": "ZONE_WEST",
                        "localname": "ZONE_WEST",
                        "longitude": null,
                        "latitude": null,
                        "label": "Zone",
                        "code": "JZN1",
                        "children": [
                            {
                                "id": "1c7d8d00-7678-4fd4-8dd2-2802daa7249b",
                                "boundaryNum": 1,
                                "name": "WARD_4",
                                "localname": "WARD_4",
                                "longitude": null,
                                "latitude": null,
                                "label": "Block",
                                "code": "WARD4",
                                "children": [
                                    {
                                        "id": "6e286d0a-d141-49b2-8d3e-35cb7251fdee",
                                        "boundaryNum": 1,
                                        "name": "Yairipok Bishnunaha Mamang Leikai, Near Yairpok Bazar",
                                        "localname": "Yairipok Bishnunaha Mamang Leikai, Near Yairpok Bazar",
                                        "longitude": null,
                                        "latitude": null,
                                        "label": "Locality",
                                        "code": "0A2",
                                        "pincode": [
                                            143001
                                        ],
                                        "area": "AREA_A",
                                        "children": []
                                    },
									{
                                        "id": "6e286d0a-d141-49b2-8d3e-35cb7251fdef",
                                        "boundaryNum": 1,
                                        "name": "Yairipok Bamon Leikai, Police Station",
                                        "localname": "Yairipok Bamon Leikai, Police Station",
                                        "longitude": null,
                                        "latitude": null,
                                        "label": "Locality",
                                        "code": "0A3",
                                        "pincode": [
                                            143001
                                        ],
                                        "area": "AREA_A",
                                        "children": []
                                    }
                                ]
                            },
							{
                                "id": "1c7d8d00-7678-4fd4-8dd2-2802daa7249b",
                                "boundaryNum": 1,
                                "name": "WARD_3",
                                "localname": "WARD_3",
                                "longitude": null,
                                "latitude": null,
                                "label": "Block",
                                "code": "WARD3",
                                "children": [
                                    {
                                        "id": "6e286d0a-d141-49b2-8d3e-35cb7251fdee",
                                        "boundaryNum": 1,
                                        "name": "Yairipok Kekhel Leikai",
                                        "localname": "Yairipok Kekhel Leikai",
                                        "longitude": null,
                                        "latitude": null,
                                        "label": "Locality",
                                        "code": "0A1",
                                        "pincode": [
                                            143001
                                        ],
                                        "area": "AREA_A",
                                        "children": []
                                    }
                                ]
                            }
                        ]
                    }
					
                ]
            }
        }
    ]
}