{
    "tenantId": "mn",
    "moduleName": "PropertyTax",
    "UsageCategory": [
        
        {
            "name": "Owner's Residential Use",
            "code": "OWNER_RESIDENTIAL",
            "active": true,
            "fromFY": "2015-16"
        },
        {
            "name": "Owner's Commercial Use",
            "code": "OWNER_COMMERCIAL",
            "active": true,
            "fromFY": "2015-16"
        },
        {
            "name": "Owner's Mixed Use",
            "code": "OWNER_MIXED",
            "active": true,
            "fromFY": "2015-16"
        },
        {
            "name": "Tenant's Residential Use",
            "code": "TENANT_RESIDENTIAL",
            "active": true,
            "fromFY": "2015-16"
        },
        {
            "name": "Tenant's Commercial Use",
            "code": "TENANT_COMMERCIAL",
            "active": true,
            "fromFY": "2015-16"
        },
		    {
            "name": "Tenant's Mixed Use",
            "code": "TENANT_MIXED",
            "active": true,
            "fromFY": "2015-16"
        },
		    {
            "name": "Used by the State Govt./Public Sector Undertaking/ Local Government owned for offices and any other purpose (including residential quarters),",
            "code": "USE_BY_STATE_GOVT",
            "active": true,
            "fromFY": "2015-16"
        },
		    {
            "name": "Used by the Departments of the Central Government",
            "code": "USE_BY_CENTRAL_GOVT",
            "active": true,
            "fromFY": "2015-16"
        }
    ]
}